quart_authlib/__init__.py
quart_authlib/apps.py
quart_authlib/integration.py
quart_authlib-0.0.3.dist-info/LICENSE
quart_authlib-0.0.3.dist-info/METADATA
quart_authlib-0.0.3.dist-info/WHEEL
quart_authlib-0.0.3.dist-info/top_level.txt
quart_authlib-0.0.3.dist-info/RECORD
