Metadata-Version: 2.1
Name: quart-authlib
Version: 0.0.3
Summary: Quart extension for the Authlib library
License: BSD 3-Clause License
Project-URL: repository, https://github.com/mcpcpc/quart-authlib
Project-URL: changelog, https://github.com/mcpcpc/quart-authlib/blob/master/CHANGELOG.md
Classifier: Environment :: Web Environment
Classifier: Intended Audience :: Developers
Classifier: License :: OSI Approved :: BSD License
Classifier: Operating System :: OS Independent
Classifier: Programming Language :: Python
Classifier: Programming Language :: Python :: 3.11
Classifier: Programming Language :: Python :: 3.12
Classifier: Programming Language :: Python :: 3.13
Classifier: Topic :: Internet :: WWW/HTTP :: Dynamic Content
Classifier: Topic :: Software Development :: Libraries :: Python Modules
Requires-Python: >=3.11
License-File: LICENSE
Requires-Dist: authlib
Requires-Dist: requests
Requires-Dist: quart
Provides-Extra: cache
Requires-Dist: cachelib; extra == "cache"
Provides-Extra: dev
Requires-Dist: black; extra == "dev"
